LICENSE
README.md
setup.cfg
setup.py
lemonbar/__init__.py
lemonbar/async_utils.py
lemonbar/command_handler.py
lemonbar/lemonbar.py
lemonbar/module.py
lemonbar.egg-info/PKG-INFO
lemonbar.egg-info/SOURCES.txt
lemonbar.egg-info/dependency_links.txt
lemonbar.egg-info/requires.txt
lemonbar.egg-info/top_level.txt
lemonbar/formatters/__init__.py
lemonbar/formatters/_formatter.py
lemonbar/formatters/attributes.py
lemonbar/formatters/basic_formatters.py
lemonbar/formatters/button.py
lemonbar/formatters/change_monitor.py
lemonbar/models/__init__.py
lemonbar/models/bar_geometry.py
lemonbar/models/bar_placement.py
lemonbar/models/lemonbar_arguments.py
lemonbar/models/monitor.py
lemonbar/modules/__init__.py
lemonbar/modules/clock.py